include/SDFC_14.4.7/sdf.h
include/SDFC_14.4.7/sdf_derived.h
include/SDFC_14.4.7/sdf_extension.h
include/SDFC_14.4.7/sdf_helper.h
include/SDFC_14.4.7/sdf_list_type.h
include/SDFC_14.4.7/sdf_vector_type.h
include/SDFC_14.4.7/stack_allocator.h
include/SDFC_14.4.7/uthash.h
lib/SDFC_14.4.7/SDFCConfig.cmake
lib/SDFC_14.4.7/SDFCConfigVersion.cmake
lib/SDFC_14.4.7/SDFCTargets-release.cmake
lib/SDFC_14.4.7/SDFCTargets.cmake
lib/SDFC_14.4.7/libsdfc.a
sdf_xarray/__init__.py
sdf_xarray/_version.py
sdf_xarray/csdf.pxd
sdf_xarray/dataset_accessor.py
sdf_xarray/download.py
sdf_xarray/plotting.py
sdf_xarray/sdf_interface.cpython-311-x86_64-linux-gnu.so
sdf_xarray/sdf_interface.pyx
sdf_xarray-0.4.0.dist-info/METADATA
sdf_xarray-0.4.0.dist-info/WHEEL
sdf_xarray-0.4.0.dist-info/entry_points.txt
sdf_xarray-0.4.0.dist-info/RECORD
sdf_xarray-0.4.0.dist-info/licenses/LICENCE
