Metadata-Version: 2.4
Name: sdf-xarray
Version: 0.4.0
Summary: Provides a backend for xarray to read SDF files as created by the EPOCH plasma PIC code.
Author-Email: Peter Hill <peter.hill@york.ac.uk>, Joel Adams <joel.adams@york.ac.uk>, Shaun Doherty <shaun.doherty@york.ac.uk>, Chris Herdman <chris.herdman@york.ac.uk>, Liam Pattinson <liam.pattinson@york.ac.uk>
License-Expression: BSD-3-Clause
Classifier: Development Status :: 5 - Production/Stable
Classifier: Intended Audience :: Science/Research
Classifier: Topic :: Scientific/Engineering
Classifier: Operating System :: OS Independent
Classifier: Programming Language :: Python
Classifier: Programming Language :: Python :: 3
Classifier: Programming Language :: Python :: 3.10
Classifier: Programming Language :: Python :: 3.11
Classifier: Programming Language :: Python :: 3.12
Classifier: Programming Language :: Python :: 3.13
Classifier: Programming Language :: Python :: 3.14
Requires-Python: <3.15,>=3.10
Requires-Dist: numpy>=2.0.0
Requires-Dist: xarray>=2024.1.0
Requires-Dist: dask>=2024.7.1
Provides-Extra: jupyter
Requires-Dist: dask[diagnostics]; extra == "jupyter"
Requires-Dist: ipykernel>=6.29.5; extra == "jupyter"
Provides-Extra: pint
Requires-Dist: pint; extra == "pint"
Requires-Dist: pint-xarray; extra == "pint"
